startlit/__init__.py
startlit/help.py
startlit/kill.py
startlit/list.py
startlit/snowflake.py
startlit/start.py
startlit-0.0.5.dist-info/LICENSE
startlit-0.0.5.dist-info/METADATA
startlit-0.0.5.dist-info/WHEEL
startlit-0.0.5.dist-info/entry_points.txt
startlit-0.0.5.dist-info/RECORD
