Metadata-Version: 2.1
Name: startlit
Version: 0.0.5
Summary: Get started with a streamlit app template code in style
Home-page: https://github.com/ineelhere/startlit
License: Apache License - Version 2.0
Author: Indraneel Chakraborty
Requires-Python: >=3.8
Classifier: License :: Other/Proprietary License
Classifier: Programming Language :: Python :: 3
Classifier: Programming Language :: Python :: 3.8
Classifier: Programming Language :: Python :: 3.9
Classifier: Programming Language :: Python :: 3.10
Classifier: Programming Language :: Python :: 3.11
Classifier: Programming Language :: Python :: 3.12
